{"coordinates": {"longitude": -86.7718357, "latitude": 33.4701325}, "term": "restaurants", "is_claimed": false, "hours": [{"is_open_now": false, "hours_type": "REGULAR", "open": [{"day": 0, "end": "2200", "is_overnight": false, "start": "1100"}, {"day": 1, "end": "2200", "is_overnight": false, "start": "1100"}, {"day": 2, "end": "2200", "is_overnight": false, "start": "1100"}, {"day": 3, "end": "2200", "is_overnight": false, "start": "1100"}, {"day": 4, "end": "2300", "is_overnight": false, "start": "1100"}, {"day": 5, "end": "2300", "is_overnight": false, "start": "0930"}, {"day": 6, "end": "2200", "is_overnight": false, "start": "0930"}]}], "categories": [{"alias": "tex-mex", "title": "Tex-Mex"}, {"alias": "mexican", "title": "Mexican"}], "name": "Cocina Superior", "review_count": 109, "image_url": "https://s3-media4.fl.yelpcdn.com/bphoto/h9N04H43mC0Be81aLxJLIQ/o.jpg", "photos": ["https://s3-media1.fl.yelpcdn.com/bphoto/h9N04H43mC0Be81aLxJLIQ/o.jpg", "https://s3-media1.fl.yelpcdn.com/bphoto/Qll0o20ttCqYV4CNOhIHow/o.jpg", "https://s3-media1.fl.yelpcdn.com/bphoto/usfZ6KEd_YXBDk5ACezKpQ/o.jpg"], "id": "cocina-superior-birmingham", "url": "https://www.yelp.com/biz/cocina-superior-birmingham?adjust_creative=92p07_JjKyriZTQxAXRiKQ&utm_campaign=yelp_api_v3&utm_medium=api_v3_business_lookup&utm_source=92p07_JjKyriZTQxAXRiKQ", "phone": "+12052591980", "price": "$$", "is_closed": false, "location": {"address1": "587 Brookwood Village", "address3": "", "country": "US", "city": "Birmingham", "address2": null, "zip_code": "35209", "state": "AL"}, "rating": 3.5}