{"coordinates": {"longitude": -105.009279227872, "latitude": 39.7562669895912}, "term": "restaurants", "is_claimed": false, "hours": [{"is_open_now": true, "hours_type": "REGULAR", "open": [{"day": 0, "start": "1100", "is_overnight": true, "end": "0200"}, {"day": 1, "start": "1100", "is_overnight": true, "end": "0200"}, {"day": 2, "start": "1100", "is_overnight": true, "end": "0200"}, {"day": 3, "start": "1100", "is_overnight": true, "end": "0200"}, {"day": 4, "start": "1100", "is_overnight": true, "end": "0200"}, {"day": 5, "start": "1100", "is_overnight": true, "end": "0200"}]}], "categories": [{"alias": "pubs", "title": "Pubs"}, {"alias": "burgers", "title": "Burgers"}], "url": "https://www.yelp.com/biz/my-brothers-bar-denver?adjust_creative=92p07_JjKyriZTQxAXRiKQ&utm_campaign=yelp_api_v3&utm_medium=api_v3_business_lookup&utm_source=92p07_JjKyriZTQxAXRiKQ", "name": "My Brother's Bar", "review_count": 544, "image_url": "https://s3-media2.fl.yelpcdn.com/bphoto/UG7zoUKsLD_xSOUL4DQ7OQ/o.jpg", "id": "my-brothers-bar-denver", "photos": ["https://s3-media4.fl.yelpcdn.com/bphoto/UG7zoUKsLD_xSOUL4DQ7OQ/o.jpg", "https://s3-media3.fl.yelpcdn.com/bphoto/GhB0UTXqrL80jMdd57Whfw/o.jpg", "https://s3-media4.fl.yelpcdn.com/bphoto/5SUUoWyRH80BC2n2MH3m6A/o.jpg"], "phone": "+13034559991", "price": "$", "is_closed": false, "location": {"state": "CO", "address1": "2376 15th St", "address3": "", "city": "Denver", "address2": "", "zip_code": "80202", "country": "US"}, "rating": 4.0}