{"coordinates": {"longitude": -0.05318, "latitude": 51.52903}, "term": "attractions", "is_claimed": false, "categories": [{"alias": "parks", "title": "Parks"}], "url": "https://www.yelp.com/biz/museum-gardens-london?adjust_creative=92p07_JjKyriZTQxAXRiKQ&utm_campaign=yelp_api_v3&utm_medium=api_v3_business_lookup&utm_source=92p07_JjKyriZTQxAXRiKQ", "name": "Museum Gardens", "review_count": 4, "image_url": "https://s3-media2.fl.yelpcdn.com/bphoto/I3A97I7Ql6ksC9hWc3MB6A/o.jpg", "id": "museum-gardens-london", "photos": ["https://s3-media4.fl.yelpcdn.com/bphoto/I3A97I7Ql6ksC9hWc3MB6A/o.jpg", "https://s3-media3.fl.yelpcdn.com/bphoto/L9_rBn4yJKFzEsyJee_J8g/o.jpg"], "phone": "", "is_closed": false, "location": {"state": "XGL", "address1": "Victoria Park Square", "address3": "", "city": "London", "address2": "", "zip_code": "E2 9PA", "country": "GB"}, "rating": 4.5}