{"coordinates": {"longitude": -122.36992, "latitude": 47.67216}, "term": "attractions", "is_claimed": true, "categories": [{"alias": "photographers", "title": "Photographers"}], "url": "https://www.yelp.com/biz/calima-portraits-seattle?adjust_creative=92p07_JjKyriZTQxAXRiKQ&utm_campaign=yelp_api_v3&utm_medium=api_v3_business_lookup&utm_source=92p07_JjKyriZTQxAXRiKQ", "review_count": 6, "image_url": "https://s3-media3.fl.yelpcdn.com/bphoto/1d98Rhcpbm57U-JzRz91aw/o.jpg", "photos": ["https://s3-media4.fl.yelpcdn.com/bphoto/1d98Rhcpbm57U-JzRz91aw/o.jpg", "https://s3-media2.fl.yelpcdn.com/bphoto/_Vxcr3P_1JnWyNJJyYOO3w/o.jpg", "https://s3-media3.fl.yelpcdn.com/bphoto/Z45hh6fxpl7kylp2CPzWBw/o.jpg"], "id": "calima-portraits-seattle", "name": "CALIMA Portraits", "phone": "+12069923792", "is_closed": false, "location": {"address1": "927 NW 60th St", "address3": "", "country": "US", "city": "Seattle", "address2": null, "zip_code": "98107", "state": "WA"}, "rating": 5.0}