{"coordinates": {"longitude": 174.7841172, "latitude": -36.9839554}, "term": "hotels", "is_claimed": false, "hours": [{"is_open_now": true, "hours_type": "REGULAR", "open": [{"day": 0, "start": "0700", "is_overnight": false, "end": "2200"}, {"day": 1, "start": "0700", "is_overnight": false, "end": "2200"}, {"day": 2, "start": "0700", "is_overnight": false, "end": "2200"}, {"day": 3, "start": "0700", "is_overnight": false, "end": "2200"}, {"day": 4, "start": "0700", "is_overnight": false, "end": "2200"}, {"day": 5, "start": "0700", "is_overnight": false, "end": "2200"}, {"day": 6, "start": "0700", "is_overnight": false, "end": "2200"}]}], "categories": [{"alias": "hotels", "title": "Hotels"}], "photos": ["https://s3-media1.fl.yelpcdn.com/bphoto/-UDBw-5Od63OlSoVu1xsvw/o.jpg", "https://s3-media2.fl.yelpcdn.com/bphoto/2BwwIagtyICwHElroXgu7g/o.jpg"], "name": "Heartland Hotel", "review_count": 2, "image_url": "https://s3-media3.fl.yelpcdn.com/bphoto/-UDBw-5Od63OlSoVu1xsvw/o.jpg", "id": "heartland-hotel-mangere", "url": "https://www.yelp.com/biz/heartland-hotel-mangere?adjust_creative=92p07_JjKyriZTQxAXRiKQ&utm_campaign=yelp_api_v3&utm_medium=api_v3_business_lookup&utm_source=92p07_JjKyriZTQxAXRiKQ", "phone": "+6492754540", "price": "$$", "is_closed": false, "location": {"address1": "14 Airpark Dr", "state": "AUK", "country": "NZ", "city": "Mangere", "address2": "", "zip_code": "2022", "address3": ""}, "rating": 5.0}