{"phone": "+18322303330", "is_claimed": true, "name": "Aim Thai Restaurant", "image_url": "https://s3-media1.fl.yelpcdn.com/bphoto/qEnFwQOhpLxoyyVaAMm5dg/o.jpg", "rating": 5.0, "url": "https://www.yelp.com/biz/aim-thai-restaurant-houston?adjust_creative=92p07_JjKyriZTQxAXRiKQ&utm_campaign=yelp_api_v3&utm_medium=api_v3_business_lookup&utm_source=92p07_JjKyriZTQxAXRiKQ", "photos": ["https://s3-media2.fl.yelpcdn.com/bphoto/qEnFwQOhpLxoyyVaAMm5dg/o.jpg", "https://s3-media4.fl.yelpcdn.com/bphoto/_8gCuL5yfjoMnrHhi8aUJw/o.jpg", "https://s3-media1.fl.yelpcdn.com/bphoto/6qJkWmr_weE0vl2yMMIa2g/o.jpg"], "location": {"city": "Houston", "country": "US", "address1": "9734 W Montgomery Rd", "address3": "", "address2": null, "state": "TX", "zip_code": "77088"}, "id": "aim-thai-restaurant-houston", "term": "restaurants", "categories": [{"alias": "thai", "title": "Thai"}], "hours": [{"is_open_now": false, "hours_type": "REGULAR", "open": [{"end": "2000", "is_overnight": false, "day": 1, "start": "1000"}, {"end": "2000", "is_overnight": false, "day": 2, "start": "1000"}, {"end": "2000", "is_overnight": false, "day": 3, "start": "1000"}, {"end": "2000", "is_overnight": false, "day": 4, "start": "1000"}, {"end": "2000", "is_overnight": false, "day": 5, "start": "1000"}, {"end": "2000", "is_overnight": false, "day": 6, "start": "1000"}]}], "is_closed": false, "price": "$", "coordinates": {"longitude": -95.4499031809509, "latitude": 29.8843021991708}, "review_count": 66}