{"phone": "+61882077000", "is_claimed": true, "name": "Art Gallery of South Australia", "image_url": "https://s3-media2.fl.yelpcdn.com/bphoto/AqYoxqbTD3zdN7InOOzv6g/o.jpg", "rating": 4.0, "url": "https://www.yelp.com/biz/art-gallery-of-south-australia-adelaide?adjust_creative=92p07_JjKyriZTQxAXRiKQ&utm_campaign=yelp_api_v3&utm_medium=api_v3_business_lookup&utm_source=92p07_JjKyriZTQxAXRiKQ", "photos": ["https://s3-media4.fl.yelpcdn.com/bphoto/AqYoxqbTD3zdN7InOOzv6g/o.jpg", "https://s3-media4.fl.yelpcdn.com/bphoto/tJZnqqdEfSF1h9iejBU4Xg/o.jpg", "https://s3-media4.fl.yelpcdn.com/bphoto/Z6yebQs1OAhwBfttDKic4Q/o.jpg"], "location": {"city": "Adelaide", "country": "AU", "address1": "North Tce", "address3": null, "address2": null, "state": "SA", "zip_code": "5000"}, "id": "art-gallery-of-south-australia-adelaide", "term": "hotels", "categories": [{"alias": "galleries", "title": "Art Galleries"}, {"alias": "tours", "title": "Tours"}], "hours": [{"is_open_now": false, "hours_type": "REGULAR", "open": [{"end": "1700", "is_overnight": false, "day": 0, "start": "1000"}, {"end": "1700", "is_overnight": false, "day": 1, "start": "1000"}, {"end": "1700", "is_overnight": false, "day": 2, "start": "1000"}, {"end": "1700", "is_overnight": false, "day": 3, "start": "1000"}, {"end": "1700", "is_overnight": false, "day": 4, "start": "1000"}, {"end": "1700", "is_overnight": false, "day": 5, "start": "1000"}, {"end": "1700", "is_overnight": false, "day": 6, "start": "1000"}]}], "is_closed": false, "price": "$", "coordinates": {"longitude": 138.602464199066, "latitude": -34.9210913394011}, "review_count": 14}