{"phone": "+61262305921", "is_claimed": true, "name": "Blackfire", "image_url": "https://s3-media2.fl.yelpcdn.com/bphoto/NFaYaf20wqF8IkZ3gKeKvw/o.jpg", "rating": 3.5, "url": "https://www.yelp.com/biz/blackfire-braddon?adjust_creative=92p07_JjKyriZTQxAXRiKQ&utm_campaign=yelp_api_v3&utm_medium=api_v3_business_lookup&utm_source=92p07_JjKyriZTQxAXRiKQ", "photos": ["https://s3-media2.fl.yelpcdn.com/bphoto/NFaYaf20wqF8IkZ3gKeKvw/o.jpg", "https://s3-media4.fl.yelpcdn.com/bphoto/aIBgFEvH41RuXLv03rLpZQ/o.jpg"], "location": {"city": "Braddon", "country": "AU", "address1": "Unit 45", "address3": "", "address2": "45/38 Mort St", "state": "ACT", "zip_code": "2612"}, "id": "blackfire-braddon", "term": "restaurants", "categories": [{"alias": "spanish", "title": "Spanish"}], "hours": [{"is_open_now": true, "hours_type": "REGULAR", "open": [{"end": "2300", "is_overnight": false, "day": 0, "start": "0800"}, {"end": "2300", "is_overnight": false, "day": 1, "start": "0800"}, {"end": "2300", "is_overnight": false, "day": 2, "start": "0800"}, {"end": "2300", "is_overnight": false, "day": 3, "start": "0800"}, {"end": "2300", "is_overnight": false, "day": 4, "start": "0800"}, {"end": "2300", "is_overnight": false, "day": 5, "start": "0800"}, {"end": "2300", "is_overnight": false, "day": 6, "start": "0800"}]}], "is_closed": false, "price": "$$$", "coordinates": {"longitude": 149.131650108765, "latitude": -35.2728535799944}, "review_count": 7}