{"rating": 4.5, "is_claimed": false, "name": "Bolton Food and Drink Festival", "phone": "", "url": "https://www.yelp.com/biz/bolton-food-and-drink-festival-bolton?adjust_creative=92p07_JjKyriZTQxAXRiKQ&utm_campaign=yelp_api_v3&utm_medium=api_v3_business_lookup&utm_source=92p07_JjKyriZTQxAXRiKQ", "is_closed": false, "location": {"city": "Bolton", "country": "GB", "address1": "Victoria Sq", "address3": "", "address2": "", "state": "XGM", "zip_code": "BL1 5"}, "id": "bolton-food-and-drink-festival-bolton", "term": "attractions", "categories": [{"alias": "festivals", "title": "Festivals"}], "photos": ["https://s3-media1.fl.yelpcdn.com/bphoto/edfbzU6hK9HjwkgT3kWnQg/o.jpg", "https://s3-media4.fl.yelpcdn.com/bphoto/_S62RgkdlTKCN4pRZ6gwvA/o.jpg", "https://s3-media1.fl.yelpcdn.com/bphoto/P8Tu-GDdf4Gwq9UsDgwDTA/o.jpg"], "image_url": "https://s3-media1.fl.yelpcdn.com/bphoto/edfbzU6hK9HjwkgT3kWnQg/o.jpg", "coordinates": {"longitude": -2.4298699, "latitude": 53.5783806}, "review_count": 5}