{"phone": "+61738589000", "is_claimed": false, "name": "Broncos Leagues Club", "rating": 3.0, "url": "https://www.yelp.com/biz/broncos-leagues-club-qld?adjust_creative=92p07_JjKyriZTQxAXRiKQ&utm_campaign=yelp_api_v3&utm_medium=api_v3_business_lookup&utm_source=92p07_JjKyriZTQxAXRiKQ", "photos": ["https://s3-media1.fl.yelpcdn.com/bphoto/V4OZVylh0EYERTikjrprHg/o.jpg", "https://s3-media2.fl.yelpcdn.com/bphoto/VwBqojGjCMvOHXFr3oiuMg/o.jpg", "https://s3-media1.fl.yelpcdn.com/bphoto/5S5Zfhsa-_JuuiMhTpIuCg/o.jpg"], "location": {"city": "QLD", "country": "AU", "address1": "Fulcher Rd", "address3": null, "address2": null, "state": "QLD", "zip_code": "4059"}, "id": "broncos-leagues-club-qld", "hours": [{"is_open_now": true, "hours_type": "REGULAR", "open": [{"end": "2200", "is_overnight": false, "day": 0, "start": "0930"}, {"end": "2200", "is_overnight": false, "day": 1, "start": "0930"}, {"end": "2200", "is_overnight": false, "day": 2, "start": "0930"}, {"end": "2200", "is_overnight": false, "day": 3, "start": "0930"}, {"end": "2200", "is_overnight": false, "day": 4, "start": "0930"}, {"end": "2200", "is_overnight": false, "day": 5, "start": "0930"}, {"end": "2200", "is_overnight": false, "day": 6, "start": "0930"}]}], "categories": [{"alias": "social_clubs", "title": "Social Clubs"}], "term": "attractions", "is_closed": false, "image_url": "https://s3-media1.fl.yelpcdn.com/bphoto/V4OZVylh0EYERTikjrprHg/o.jpg", "coordinates": {"longitude": 152.9958801, "latitude": -27.4484901}, "review_count": 9}