{"phone": "+18772108700", "is_claimed": false, "name": "Camp Lord Willing RV Park & Campground", "rating": 3.5, "url": "https://www.yelp.com/biz/camp-lord-willing-rv-park-and-campground-monroe?adjust_creative=92p07_JjKyriZTQxAXRiKQ&utm_campaign=yelp_api_v3&utm_medium=api_v3_business_lookup&utm_source=92p07_JjKyriZTQxAXRiKQ", "photos": [], "location": {"city": "Monroe", "country": "US", "address1": "1600 Stumpmier Rd", "address3": "", "address2": "", "state": "MI", "zip_code": "48162"}, "id": "camp-lord-willing-rv-park-and-campground-monroe", "hours": [{"is_open_now": false, "hours_type": "REGULAR", "open": [{"end": "1800", "is_overnight": false, "day": 0, "start": "1200"}, {"end": "1800", "is_overnight": false, "day": 1, "start": "1200"}, {"end": "1800", "is_overnight": false, "day": 2, "start": "1200"}, {"end": "2000", "is_overnight": false, "day": 3, "start": "1200"}, {"end": "2000", "is_overnight": false, "day": 4, "start": "1200"}, {"end": "1600", "is_overnight": false, "day": 5, "start": "1200"}, {"end": "1700", "is_overnight": false, "day": 6, "start": "1300"}]}], "categories": [{"alias": "rvparks", "title": "RV Parks"}, {"alias": "campgrounds", "title": "Campgrounds"}], "term": "attractions", "is_closed": false, "image_url": "", "coordinates": {"longitude": -83.3996722439686, "latitude": 41.9779628079579}, "review_count": 3}