{"coordinates": {"longitude": -71.0947599, "latitude": 42.3293899}, "term": "attractions", "is_claimed": true, "categories": [{"alias": "guesthouses", "title": "Guest Houses"}], "url": "https://www.yelp.com/biz/fort-hill-inn-boston?adjust_creative=92p07_JjKyriZTQxAXRiKQ&utm_campaign=yelp_api_v3&utm_medium=api_v3_business_lookup&utm_source=92p07_JjKyriZTQxAXRiKQ", "name": "Fort Hill Inn", "review_count": 7, "image_url": "https://s3-media3.fl.yelpcdn.com/bphoto/KbKbyDjJE5zQRcO0hQelig/o.jpg", "id": "fort-hill-inn-boston", "photos": ["https://s3-media3.fl.yelpcdn.com/bphoto/KbKbyDjJE5zQRcO0hQelig/o.jpg", "https://s3-media2.fl.yelpcdn.com/bphoto/E5FMhYG7dspx2Cl-xkjuKA/o.jpg", "https://s3-media3.fl.yelpcdn.com/bphoto/LMfFvKjbz3WaBLrnuGq4og/o.jpg"], "phone": "+16173125925", "is_closed": false, "location": {"address1": "3 Centre Pl", "address3": "", "country": "US", "city": "Boston", "address2": "", "zip_code": "02119", "state": "MA"}, "rating": 4.5}