{"coordinates": {"longitude": -71.08083, "latitude": 42.34504}, "term": "attractions", "is_claimed": false, "hours": [{"is_open_now": true, "hours_type": "REGULAR", "open": [{"day": 0, "start": "0700", "is_overnight": false, "end": "2200"}, {"day": 1, "start": "0700", "is_overnight": true, "end": "0200"}, {"day": 2, "start": "0700", "is_overnight": true, "end": "0200"}, {"day": 3, "start": "0700", "is_overnight": true, "end": "0200"}, {"day": 4, "start": "0700", "is_overnight": true, "end": "0200"}, {"day": 5, "start": "0700", "is_overnight": true, "end": "0200"}, {"day": 6, "start": "0700", "is_overnight": false, "end": "2200"}]}], "categories": [{"alias": "hotels", "title": "Hotels"}], "url": "https://www.yelp.com/biz/inn-st-botolph-boston?adjust_creative=92p07_JjKyriZTQxAXRiKQ&utm_campaign=yelp_api_v3&utm_medium=api_v3_business_lookup&utm_source=92p07_JjKyriZTQxAXRiKQ", "name": "Inn @ St. Botolph", "review_count": 32, "image_url": "https://s3-media3.fl.yelpcdn.com/bphoto/Yf8sqVBcrIzG7iEy3VKv1w/o.jpg", "id": "inn-st-botolph-boston", "photos": ["https://s3-media3.fl.yelpcdn.com/bphoto/Yf8sqVBcrIzG7iEy3VKv1w/o.jpg", "https://s3-media4.fl.yelpcdn.com/bphoto/QOq9bXXyoY4eBI3uR_Sdag/o.jpg", "https://s3-media1.fl.yelpcdn.com/bphoto/5bNAn3FTerVQmDk8HPgPzw/o.jpg"], "phone": "+16172368099", "price": "$$", "is_closed": false, "location": {"address1": "99 St Botolph St", "address3": "", "country": "US", "city": "Boston", "address2": null, "zip_code": "02116", "state": "MA"}, "rating": 4.5}