{"coordinates": {"longitude": -82.88163, "latitude": 42.59712}, "term": "attractions", "is_claimed": true, "hours": [{"is_open_now": false, "hours_type": "REGULAR", "open": [{"day": 1, "end": "1700", "is_overnight": false, "start": "1000"}, {"day": 2, "end": "1700", "is_overnight": false, "start": "1000"}, {"day": 3, "end": "1700", "is_overnight": false, "start": "1000"}, {"day": 4, "end": "1700", "is_overnight": false, "start": "1000"}]}], "categories": [{"alias": "photographers", "title": "Photographers"}], "url": "https://www.yelp.com/biz/kateri-shue-photography-mount-clemens?adjust_creative=92p07_JjKyriZTQxAXRiKQ&utm_campaign=yelp_api_v3&utm_medium=api_v3_business_lookup&utm_source=92p07_JjKyriZTQxAXRiKQ", "name": "Kateri Shue Photography", "review_count": 2, "image_url": "https://s3-media2.fl.yelpcdn.com/bphoto/vubsQ962rTaUbdlNBN9kJA/o.jpg", "id": "kateri-shue-photography-mount-clemens", "photos": ["https://s3-media4.fl.yelpcdn.com/bphoto/vubsQ962rTaUbdlNBN9kJA/o.jpg", "https://s3-media4.fl.yelpcdn.com/bphoto/cE9doS4amn_9KUXKyXnj3w/o.jpg", "https://s3-media4.fl.yelpcdn.com/bphoto/x-DDBz-PO-taHVm8V9mltQ/o.jpg"], "phone": "+15867450646", "is_closed": false, "location": {"address1": null, "address3": "", "country": "US", "city": "Mount Clemens", "address2": null, "zip_code": "48043", "state": "MI"}, "rating": 5.0}