{"coordinates": {"longitude": -2.9840701, "latitude": 53.4064903}, "term": "restaurants", "is_claimed": true, "hours": [{"is_open_now": false, "hours_type": "REGULAR", "open": [{"day": 0, "end": "1630", "is_overnight": false, "start": "0630"}, {"day": 1, "end": "1630", "is_overnight": false, "start": "0630"}, {"day": 2, "end": "1630", "is_overnight": false, "start": "0630"}, {"day": 3, "end": "1630", "is_overnight": false, "start": "0630"}, {"day": 4, "end": "1630", "is_overnight": false, "start": "0630"}, {"day": 5, "end": "1630", "is_overnight": false, "start": "0630"}]}], "categories": [{"alias": "delis", "title": "Delis"}, {"alias": "sandwiches", "title": "Sandwiches"}, {"alias": "butcher", "title": "Butcher"}], "url": "https://www.yelp.com/biz/richmond-deli-liverpool?adjust_creative=92p07_JjKyriZTQxAXRiKQ&utm_campaign=yelp_api_v3&utm_medium=api_v3_business_lookup&utm_source=92p07_JjKyriZTQxAXRiKQ", "name": "Richmond Deli", "review_count": 6, "image_url": "https://s3-media3.fl.yelpcdn.com/bphoto/edI-g1f_oYqYUVdsLwFm9w/o.jpg", "id": "richmond-deli-liverpool", "photos": ["https://s3-media4.fl.yelpcdn.com/bphoto/edI-g1f_oYqYUVdsLwFm9w/o.jpg", "https://s3-media3.fl.yelpcdn.com/bphoto/GbOm10kkw0E5lbaLbEDb9Q/o.jpg", "https://s3-media1.fl.yelpcdn.com/bphoto/tuLQ_CFHFJSRwSeqGWuFOQ/o.jpg"], "phone": "+441517089729", "price": "\u00a3", "is_closed": false, "location": {"address1": "7 Richmond Street", "address3": "", "country": "GB", "city": "Liverpool", "address2": "", "zip_code": "L1 1EE", "state": "XMS"}, "rating": 4.5}