{"coordinates": {"longitude": -71.035391910813, "latitude": 42.331400342632}, "term": "restaurants", "is_claimed": true, "hours": [{"is_open_now": false, "hours_type": "REGULAR", "open": [{"day": 0, "end": "2000", "is_overnight": false, "start": "0600"}, {"day": 1, "end": "2000", "is_overnight": false, "start": "0600"}, {"day": 2, "end": "2000", "is_overnight": false, "start": "0600"}, {"day": 3, "end": "2000", "is_overnight": false, "start": "0600"}, {"day": 4, "end": "2000", "is_overnight": false, "start": "0600"}, {"day": 5, "end": "2000", "is_overnight": false, "start": "0600"}, {"day": 6, "end": "1400", "is_overnight": false, "start": "1000"}]}], "categories": [{"alias": "pizza", "title": "Pizza"}, {"alias": "italian", "title": "Italian"}], "url": "https://www.yelp.com/biz/sals-ristorante-and-pizzeria-boston?adjust_creative=92p07_JjKyriZTQxAXRiKQ&utm_campaign=yelp_api_v3&utm_medium=api_v3_business_lookup&utm_source=92p07_JjKyriZTQxAXRiKQ", "name": "Sal's Ristorante & Pizzeria", "review_count": 39, "image_url": "https://s3-media4.fl.yelpcdn.com/bphoto/y8nLGloI2aXtpmOeDduBaA/o.jpg", "id": "sals-ristorante-and-pizzeria-boston", "photos": ["https://s3-media4.fl.yelpcdn.com/bphoto/y8nLGloI2aXtpmOeDduBaA/o.jpg", "https://s3-media4.fl.yelpcdn.com/bphoto/0iD4SRmtEJW82lQOq2mlaw/o.jpg"], "phone": "+16172685800", "price": "$", "is_closed": false, "location": {"address1": "205 L St", "address3": "", "country": "US", "city": "Boston", "address2": "", "zip_code": "02127", "state": "MA"}, "rating": 3.5}